rtl/pulse_detector.v
module pulse_detector #(
    parameter DATA_WIDTH   = 16,
    parameter BUFFER_DEPTH = 256, 
    parameter PTR_WIDTH    = 8 
)(
    // Clock & Reset
    input  wire                   clk,
    input  wire                   rst_n,

    // Sample input
    input  wire [DATA_WIDTH-1:0]  sample,
    input  wire                   sample_valid,

    // Configuration
    input  wire [DATA_WIDTH-1:0]  threshold,    // detection level
    input  wire [DATA_WIDTH-1:0]  hysteresis,   // deadband below threshold
    input  wire [PTR_WIDTH-1:0]   pre_samples,  // samples to keep before trigger
    input  wire [PTR_WIDTH-1:0]   post_samples, // samples to capture after trigger
    input  wire                   enable,        // global enable

    // Outputs
    output reg                    trigger_flag,  // pulsed 1 clk when trigger fires
    output reg  [31:0]            trigger_time,  // free running timestamp
    output reg  [PTR_WIDTH-1:0]   buf_ptr_start, // start pointer of captured window
    output reg  [PTR_WIDTH-1:0]   buf_ptr_end,   // end pointer of captured window
    output reg                    capture_done,  // high when post-capture complete

    // Circular buffer read port 
    input  wire [PTR_WIDTH-1:0]   rd_addr,
    output wire [DATA_WIDTH-1:0]  rd_data
);

// ---------------------------------------------------------------------------
// 1. CIRCULAR BUFFER (simple dual-port BRAM inferred)
// ---------------------------------------------------------------------------
reg [DATA_WIDTH-1:0] circ_buf [0:BUFFER_DEPTH-1];
reg [PTR_WIDTH-1:0]  wr_ptr;

assign rd_data = circ_buf[rd_addr];

always @(posedge clk) begin
    if (sample_valid && enable)
        circ_buf[wr_ptr] <= sample;
end

// ---------------------------------------------------------------------------
// 2. STATE MACHINE
// ---------------------------------------------------------------------------
// States
localparam IDLE      = 2'd0;
localparam ARMED     = 2'd1; 
localparam CAPTURING = 2'd2; 
localparam DONE      = 2'd3; 

reg [1:0]           state;
reg [PTR_WIDTH-1:0] post_cnt;
reg [31:0]          timestamp;

wire above_threshold  = (sample >= threshold);
wire below_hysteresis = (sample <= (threshold - hysteresis));

always @(posedge clk or negedge rst_n) begin
    if (!rst_n) begin
        state         <= IDLE;
        wr_ptr        <= 0;
        post_cnt      <= 0;
        timestamp     <= 0;
        trigger_flag  <= 0;
        trigger_time  <= 0;
        buf_ptr_start <= 0;
        buf_ptr_end   <= 0;
        capture_done  <= 0;
    end else begin
        timestamp <= timestamp + 1;

        trigger_flag <= 0;

        if (!enable) begin
            state        <= IDLE;
            capture_done <= 0;
        end else if (sample_valid) begin
            wr_ptr <= wr_ptr + 1;

            case (state)
                // ── IDLE: wait for sample to cross threshold ──────────────
                IDLE: begin
                    capture_done <= 0;
                    if (above_threshold) begin
                        state        <= ARMED;
                        trigger_flag <= 1;
                        trigger_time <= timestamp;
                        // pre_samples back from CURRENT wr_ptr
                        buf_ptr_start <= wr_ptr - pre_samples;
                        post_cnt      <= 0;
                    end
                end

                // ── ARMED: signal is high, wait for it to drop ────────────
                ARMED: begin
                    if (below_hysteresis)
                        state <= CAPTURING;
                end

                // ── CAPTURING: collect post_samples more samples ──────────
                CAPTURING: begin
                    post_cnt <= post_cnt + 1;
                    if (post_cnt >= post_samples - 1) begin
                        buf_ptr_end  <= wr_ptr;
                        capture_done <= 1;
                        state        <= DONE;
                    end
                end

                // ── DONE: wait for software to re-arm (toggle enable) ─────
                DONE: begin
                    capture_done <= 1;
                    // Re-arm: software clears enable then sets it again
                end

                default: state <= IDLE;
            endcase
        end
    end
end

endmodule

sim/tb_pulse_detector.v
// =============================================================================
// Testbench: tb_pulse_detector
// =============================================================================
`timescale 1ns/1ps

module tb_pulse_detector;

localparam DATA_WIDTH   = 16;
localparam BUFFER_DEPTH = 256;
localparam PTR_WIDTH    = 8;
localparam CLK_PERIOD   = 10;

reg                    clk          = 0;
reg                    rst_n        = 0;
reg  [DATA_WIDTH-1:0]  sample       = 0;
reg                    sample_valid = 0;
reg  [DATA_WIDTH-1:0]  threshold    = 1000;
reg  [DATA_WIDTH-1:0]  hysteresis   = 100;
reg  [PTR_WIDTH-1:0]   pre_samples  = 8;
reg  [PTR_WIDTH-1:0]   post_samples = 16;
reg                    enable       = 0;
reg  [PTR_WIDTH-1:0]   rd_addr      = 0;

wire                   trigger_flag;
wire [31:0]            trigger_time;
wire [PTR_WIDTH-1:0]   buf_ptr_start;
wire [PTR_WIDTH-1:0]   buf_ptr_end;
wire                   capture_done;
wire [DATA_WIDTH-1:0]  rd_data;

// Latch trigger_flag bo pulsuje tylko 1 takt
reg trigger_seen = 0;
always @(posedge clk) begin
    if (!rst_n)
        trigger_seen <= 0;
    else if (trigger_flag)
        trigger_seen <= 1;
end

pulse_detector #(
    .DATA_WIDTH   (DATA_WIDTH),
    .BUFFER_DEPTH (BUFFER_DEPTH),
    .PTR_WIDTH    (PTR_WIDTH)
) dut (
    .clk           (clk),
    .rst_n         (rst_n),
    .sample        (sample),
    .sample_valid  (sample_valid),
    .threshold     (threshold),
    .hysteresis    (hysteresis),
    .pre_samples   (pre_samples),
    .post_samples  (post_samples),
    .enable        (enable),
    .trigger_flag  (trigger_flag),
    .trigger_time  (trigger_time),
    .buf_ptr_start (buf_ptr_start),
    .buf_ptr_end   (buf_ptr_end),
    .capture_done  (capture_done),
    .rd_addr       (rd_addr),
    .rd_data       (rd_data)
);

always #(CLK_PERIOD/2) clk = ~clk;

task send_sample;
    input [DATA_WIDTH-1:0] s;
    begin
        @(posedge clk);
        sample       <= s;
        sample_valid <= 1;
        @(posedge clk);
        sample_valid <= 0;
    end
endtask

task wait_clk;
    input integer n;
    begin
        repeat(n) @(posedge clk);
    end
endtask

integer i;
integer errors = 0;

initial begin
    $display("=== TB START: pulse_detector ===");

    // 1. Reset
    rst_n  = 0;
    enable = 0;
    wait_clk(5);
    rst_n = 1;
    wait_clk(2);
    $display("[%0t] Reset released", $time);

    // 2. Baseline samples
    enable = 1;
    trigger_seen = 0;
    $display("[%0t] Sending 20 baseline samples (value=500)", $time);
    for (i = 0; i < 20; i = i+1)
        send_sample(16'd500);

    // 3. Trigger sample
    $display("[%0t] Sending trigger sample (value=1200 > threshold=1000)", $time);
    send_sample(16'd1200);
    // Czekaj max 5 taktow na trigger_seen (latch)
    wait_clk(5);

    if (trigger_seen !== 1) begin
        $display("ERROR: trigger_flag not seen after threshold crossing!");
        errors = errors + 1;
    end else
        $display("[%0t] PASS: trigger_flag asserted, trigger_time=%0d",
                  $time, trigger_time);

    // 4. Utrzymaj wysoki, potem spadnij ponizej histerezy
    repeat(5) send_sample(16'd1200);
    $display("[%0t] Dropping below hysteresis (value=850)", $time);
    send_sample(16'd850);

    // 5. Czekaj na capture_done
    repeat(post_samples + 5) send_sample(16'd500);
    wait_clk(5);

    if (capture_done !== 1) begin
        $display("ERROR: capture_done not set!");
        errors = errors + 1;
    end else
        $display("[%0t] PASS: capture_done asserted. buf[%0d..%0d]",
                  $time, buf_ptr_start, buf_ptr_end);

    // 6. Odczyt bufora
    $display("[%0t] Reading full capture window buf[%0d..%0d]:", $time, buf_ptr_start, buf_ptr_end);
    for (i = buf_ptr_start; i <= buf_ptr_end; i = i+1) begin
        rd_addr = i;
        @(posedge clk); #1;
        $display("  buf[%0d] = %0d", rd_addr, rd_data);
    end

    // 7. Re-arm
    enable = 0; wait_clk(2);
    trigger_seen = 0;
    enable = 1; wait_clk(2);
    $display("[%0t] Re-armed", $time);

    // 8. Brak triggera gdy enable=0
    enable = 0;
    send_sample(16'd2000);
    wait_clk(5);
    if (trigger_seen !== 0) begin
        $display("ERROR: trigger_flag set while enable=0!");
        errors = errors + 1;
    end else
        $display("[%0t] PASS: no trigger when disabled", $time);

    wait_clk(10);
    if (errors == 0)
        $display("=== ALL TESTS PASSED ===");
    else
        $display("=== %0d TEST(S) FAILED ===", errors);

    $finish;
end

initial begin
    #500000;
    $display("TIMEOUT!");
    $finish;
end

initial begin
    $dumpfile("tb_pulse_detector.vcd");
    $dumpvars(0, tb_pulse_detector);
end

endmodule

sim/vivado_sim/pulse_detector_sim.sim/sim_1/behav/xsim/tb_pulse_detector.vcd
$date
   Thu Jun 18 18:43:08 2026
$end

$version
  2024.2.0
  $dumpfile ("tb_pulse_detector.vcd") 
$end

$timescale
  1ps
$end

$scope module tb_pulse_detector $end
$var reg 1 ! clk $end
$var reg 1 " rst_n $end
$var reg 16 # sample [15:0] $end
$var reg 1 $ sample_valid $end
$var reg 16 % threshold [15:0] $end
$var reg 16 & hysteresis [15:0] $end
$var reg 8 ' pre_samples [7:0] $end
$var reg 8 ( post_samples [7:0] $end
$var reg 1 ) enable $end
$var reg 8 * rd_addr [7:0] $end
$var wire 1 + trigger_flag $end
$var wire 32 , trigger_time [31:0] $end
$var wire 8 - buf_ptr_start [7:0] $end
$var wire 8 . buf_ptr_end [7:0] $end
$var wire 1 / capture_done $end
$var wire 16 0 rd_data [15:0] $end
$var reg 1 1 trigger_seen $end
$var integer 32 2 i [31:0] $end
$var integer 32 3 errors [31:0] $end
$scope module dut $end
$var wire 1 4 clk $end
$var wire 1 5 rst_n $end
$var wire 16 6 sample [15:0] $end
$var wire 1 7 sample_valid $end
$var wire 16 8 threshold [15:0] $end
$var wire 16 9 hysteresis [15:0] $end
$var wire 8 : pre_samples [7:0] $end
$var wire 8 ; post_samples [7:0] $end
$var wire 1 < enable $end
$var reg 1 = trigger_flag $end
$var reg 32 > trigger_time [31:0] $end
$var reg 8 ? buf_ptr_start [7:0] $end
$var reg 8 @ buf_ptr_end [7:0] $end
$var reg 1 A capture_done $end
$var wire 8 B rd_addr [7:0] $end
$var wire 16 0 rd_data [15:0] $end
$var reg 8 C wr_ptr [7:0] $end
$var reg 2 D state [1:0] $end
$var reg 8 E post_cnt [7:0] $end
$var reg 32 F timestamp [31:0] $end
$var wire 1 G above_threshold $end
$var wire 1 H below_hysteresis $end
$upscope $end
$scope task send_sample $end
$var reg 16 I s [15:0] $end
$upscope $end
$scope task wait_clk $end
$var integer 32 J n [31:0] $end
$upscope $end
$upscope $end
$enddefinitions $end

#0
$dumpvars
0!
0"
b0 #
0$
b1111101000 %
b1100100 &
b1000 '
b10000 (
0)
b0 *
0+
b0 ,
b0 -
b0 .
0/
bx 0
01
bx 2
b0 3
04
05
b0 6
07
b1111101000 8
b1100100 9
b1000 :
b10000 ;
0<
0=
b0 >
b0 ?
b0 @
0A
b0 B
b0 C
b0 D
b0 E
b0 F
0G
1H
bx I
b101 J
$end

#5000
1!
14

#10000
0!
04

#15000
1!
14

#20000
0!
04

#25000
1!
14

#30000
0!
04

#35000
1!
14

#40000
0!
04

#45000
1!
1"
14
15
b1 F
b10 J

#50000
0!
04

#55000
1!
14
b10 F

#60000
0!
04

#65000
1!
1)
b0 2
14
1<
b11 F
b111110100 I

#70000
0!
04

#75000
1!
b111110100 #
1$
14
b111110100 6
17
b100 F

#80000
0!
04

#85000
1!
0$
b111110100 0
b1 2
14
07
b1 C
b101 F

#90000
0!
04

#95000
1!
1$
14
17
b110 F

#100000
0!
04

#105000
1!
0$
b10 2
14
07
b10 C
b111 F

#110000
0!
04

#115000
1!
1$
14
17
b1000 F

#120000
0!
04

#125000
1!
0$
b11 2
14
07
b11 C
b1001 F

#130000
0!
04

#135000
1!
1$
14
17
b1010 F

#140000
0!
04

#145000
1!
0$
b100 2
14
07
b100 C
b1011 F

#150000
0!
04

#155000
1!
1$
14
17
b1100 F

#160000
0!
04

#165000
1!
0$
b101 2
14
07
b101 C
b1101 F

#170000
0!
04

#175000
1!
1$
14
17
b1110 F

#180000
0!
04

#185000
1!
0$
b110 2
14
07
b110 C
b1111 F

#190000
0!
04

#195000
1!
1$
14
17
b10000 F

#200000
0!
04

#205000
1!
0$
b111 2
14
07
b111 C
b10001 F

#210000
0!
04

#215000
1!
1$
14
17
b10010 F

#220000
0!
04

#225000
1!
0$
b1000 2
14
07
b1000 C
b10011 F

#230000
0!
04

#235000
1!
1$
14
17
b10100 F

#240000
0!
04

#245000
1!
0$
b1001 2
14
07
b1001 C
b10101 F

#250000
0!
04

#255000
1!
1$
14
17
b10110 F

#260000
0!
04

#265000
1!
0$
b1010 2
14
07
b1010 C
b10111 F

#270000
0!
04

#275000
1!
1$
14
17
b11000 F

#280000
0!
04

#285000
1!
0$
b1011 2
14
07
b1011 C
b11001 F

#290000
0!
04

#295000
1!
1$
14
17
b11010 F

#300000
0!
04

#305000
1!
0$
b1100 2
14
07
b1100 C
b11011 F

#310000
0!
04

#315000
1!
1$
14
17
b11100 F

#320000
0!
04

#325000
1!
0$
b1101 2
14
07
b1101 C
b11101 F

#330000
0!
04

#335000
1!
1$
14
17
b11110 F

#340000
0!
04

#345000
1!
0$
b1110 2
14
07
b1110 C
b11111 F

#350000
0!
04

#355000
1!
1$
14
17
b100000 F

#360000
0!
04

#365000
1!
0$
b1111 2
14
07
b1111 C
b100001 F

#370000
0!
04

#375000
1!
1$
14
17
b100010 F

#380000
0!
04

#385000
1!
0$
b10000 2
14
07
b10000 C
b100011 F

#390000
0!
04

#395000
1!
1$
14
17
b100100 F

#400000
0!
04

#405000
1!
0$
b10001 2
14
07
b10001 C
b100101 F

#410000
0!
04

#415000
1!
1$
14
17
b100110 F

#420000
0!
04

#425000
1!
0$
b10010 2
14
07
b10010 C
b100111 F

#430000
0!
04

#435000
1!
1$
14
17
b101000 F

#440000
0!
04

#445000
1!
0$
b10011 2
14
07
b10011 C
b101001 F

#450000
0!
04

#455000
1!
1$
14
17
b101010 F

#460000
0!
04

#465000
1!
0$
b10100 2
14
07
b10100 C
b101011 F
b10010110000 I

#470000
0!
04

#475000
1!
b10010110000 #
1$
14
b10010110000 6
17
b101100 F
1G
0H

#480000
0!
04

#485000
1!
0$
1+
b101100 ,
b1100 -
14
07
1=
b101100 >
b1100 ?
b10101 C
b1 D
b101101 F
b101 J

#490000
0!
04

#495000
1!
0+
11
14
0=
b101110 F

#500000
0!
04

#505000
1!
14
b101111 F

#510000
0!
04

#515000
1!
14
b110000 F

#520000
0!
04

#525000
1!
14
b110001 F

#530000
0!
04

#535000
1!
14
b110010 F

#540000
0!
04

#545000
1!
1$
14
17
b110011 F

#550000
0!
04

#555000
1!
0$
14
07
b10110 C
b110100 F

#560000
0!
04

#565000
1!
1$
14
17
b110101 F

#570000
0!
04

#575000
1!
0$
14
07
b10111 C
b110110 F

#580000
0!
04

#585000
1!
1$
14
17
b110111 F

#590000
0!
04

#595000
1!
0$
14
07
b11000 C
b111000 F

#600000
0!
04

#605000
1!
1$
14
17
b111001 F

#610000
0!
04

#615000
1!
0$
14
07
b11001 C
b111010 F

#620000
0!
04

#625000
1!
1$
14
17
b111011 F

#630000
0!
04

#635000
1!
0$
14
07
b11010 C
b111100 F
b1101010010 I

#640000
0!
04

#645000
1!
b1101010010 #
1$
14
b1101010010 6
17
b111101 F
0G
1H

#650000
0!
04

#655000
1!
0$
14
07
b11011 C
b10 D
b111110 F
b111110100 I

#660000
0!
04

#665000
1!
b111110100 #
1$
14
b111110100 6
17
b111111 F

#670000
0!
04

#675000
1!
0$
14
07
b11100 C
b1 E
b1000000 F

#680000
0!
04

#685000
1!
1$
14
17
b1000001 F

#690000
0!
04

#695000
1!
0$
14
07
b11101 C
b10 E
b1000010 F

#700000
0!
04

#705000
1!
1$
14
17
b1000011 F

#710000
0!
04

#715000
1!
0$
14
07
b11110 C
b11 E
b1000100 F

#720000
0!
04

#725000
1!
1$
14
17
b1000101 F

#730000
0!
04

#735000
1!
0$
14
07
b11111 C
b100 E
b1000110 F

#740000
0!
04

#745000
1!
1$
14
17
b1000111 F

#750000
0!
04

#755000
1!
0$
14
07
b100000 C
b101 E
b1001000 F

#760000
0!
04

#765000
1!
1$
14
17
b1001001 F

#770000
0!
04

#775000
1!
0$
14
07
b100001 C
b110 E
b1001010 F

#780000
0!
04

#785000
1!
1$
14
17
b1001011 F

#790000
0!
04

#795000
1!
0$
14
07
b100010 C
b111 E
b1001100 F

#800000
0!
04

#805000
1!
1$
14
17
b1001101 F

#810000
0!
04

#815000
1!
0$
14
07
b100011 C
b1000 E
b1001110 F

#820000
0!
04

#825000
1!
1$
14
17
b1001111 F

#830000
0!
04

#835000
1!
0$
14
07
b100100 C
b1001 E
b1010000 F

#840000
0!
04

#845000
1!
1$
14
17
b1010001 F

#850000
0!
04

#855000
1!
0$
14
07
b100101 C
b1010 E
b1010010 F

#860000
0!
04

#865000
1!
1$
14
17
b1010011 F

#870000
0!
04

#875000
1!
0$
14
07
b100110 C
b1011 E
b1010100 F

#880000
0!
04

#885000
1!
1$
14
17
b1010101 F

#890000
0!
04

#895000
1!
0$
14
07
b100111 C
b1100 E
b1010110 F

#900000
0!
04

#905000
1!
1$
14
17
b1010111 F

#910000
0!
04

#915000
1!
0$
14
07
b101000 C
b1101 E
b1011000 F

#920000
0!
04

#925000
1!
1$
14
17
b1011001 F

#930000
0!
04

#935000
1!
0$
14
07
b101001 C
b1110 E
b1011010 F

#940000
0!
04

#945000
1!
1$
14
17
b1011011 F

#950000
0!
04

#955000
1!
0$
14
07
b101010 C
b1111 E
b1011100 F

#960000
0!
04

#965000
1!
1$
14
17
b1011101 F

#970000
0!
04

#975000
1!
0$
b101010 .
1/
14
07
b101010 @
1A
b101011 C
b11 D
b10000 E
b1011110 F

#980000
0!
04

#985000
1!
1$
14
17
b1011111 F

#990000
0!
04

#995000
1!
0$
14
07
b101100 C
b1100000 F

#1000000
0!
04

#1005000
1!
1$
14
17
b1100001 F

#1010000
0!
04

#1015000
1!
0$
14
07
b101101 C
b1100010 F

#1020000
0!
04

#1025000
1!
1$
14
17
b1100011 F

#1030000
0!
04

#1035000
1!
0$
14
07
b101110 C
b1100100 F

#1040000
0!
04

#1045000
1!
1$
14
17
b1100101 F

#1050000
0!
04

#1055000
1!
0$
14
07
b101111 C
b1100110 F

#1060000
0!
04

#1065000
1!
1$
14
17
b1100111 F

#1070000
0!
04

#1075000
1!
0$
14
07
b110000 C
b1101000 F

#1080000
0!
04

#1085000
1!
14
b1101001 F

#1090000
0!
04

#1095000
1!
14
b1101010 F

#1100000
0!
04

#1105000
1!
14
b1101011 F

#1110000
0!
04

#1115000
1!
14
b1101100 F

#1120000
0!
04

#1125000
1!
b1100 *
b1100 2
14
b1100 B
b1101101 F

#1130000
0!
04

#1135000
1!
14
b1101110 F

#1136000
b1101 *
b1101 2
b1101 B

#1140000
0!
04

#1145000
1!
14
b1101111 F

#1146000
b1110 *
b1110 2
b1110 B

#1150000
0!
04

#1155000
1!
14
b1110000 F

#1156000
b1111 *
b1111 2
b1111 B

#1160000
0!
04

#1165000
1!
14
b1110001 F

#1166000
b10000 *
b10000 2
b10000 B

#1170000
0!
04

#1175000
1!
14
b1110010 F

#1176000
b10001 *
b10001 2
b10001 B

#1180000
0!
04

#1185000
1!
14
b1110011 F

#1186000
b10010 *
b10010 2
b10010 B

#1190000
0!
04

#1195000
1!
14
b1110100 F

#1196000
b10011 *
b10011 2
b10011 B

#1200000
0!
04

#1205000
1!
14
b1110101 F

#1206000
b10100 *
b10010110000 0
b10100 2
b10100 B

#1210000
0!
04

#1215000
1!
14
b1110110 F

#1216000
b10101 *
b10101 2
b10101 B

#1220000
0!
04

#1225000
1!
14
b1110111 F

#1226000
b10110 *
b10110 2
b10110 B

#1230000
0!
04

#1235000
1!
14
b1111000 F

#1236000
b10111 *
b10111 2
b10111 B

#1240000
0!
04

#1245000
1!
14
b1111001 F

#1246000
b11000 *
b11000 2
b11000 B

#1250000
0!
04

#1255000
1!
14
b1111010 F

#1256000
b11001 *
b11001 2
b11001 B

#1260000
0!
04

#1265000
1!
14
b1111011 F

#1266000
b11010 *
b1101010010 0
b11010 2
b11010 B

#1270000
0!
04

#1275000
1!
14
b1111100 F

#1276000
b11011 *
b111110100 0
b11011 2
b11011 B

#1280000
0!
04

#1285000
1!
14
b1111101 F

#1286000
b11100 *
b11100 2
b11100 B

#1290000
0!
04

#1295000
1!
14
b1111110 F

#1296000
b11101 *
b11101 2
b11101 B

#1300000
0!
04

#1305000
1!
14
b1111111 F

#1306000
b11110 *
b11110 2
b11110 B

#1310000
0!
04

#1315000
1!
14
b10000000 F

#1316000
b11111 *
b11111 2
b11111 B

#1320000
0!
04

#1325000
1!
14
b10000001 F

#1326000
b100000 *
b100000 2
b100000 B

#1330000
0!
04

#1335000
1!
14
b10000010 F

#1336000
b100001 *
b100001 2
b100001 B

#1340000
0!
04

#1345000
1!
14
b10000011 F

#1346000
b100010 *
b100010 2
b100010 B

#1350000
0!
04

#1355000
1!
14
b10000100 F

#1356000
b100011 *
b100011 2
b100011 B

#1360000
0!
04

#1365000
1!
14
b10000101 F

#1366000
b100100 *
b100100 2
b100100 B

#1370000
0!
04

#1375000
1!
14
b10000110 F

#1376000
b100101 *
b100101 2
b100101 B

#1380000
0!
04

#1385000
1!
14
b10000111 F

#1386000
b100110 *
b100110 2
b100110 B

#1390000
0!
04

#1395000
1!
14
b10001000 F

#1396000
b100111 *
b100111 2
b100111 B

#1400000
0!
04

#1405000
1!
14
b10001001 F

#1406000
b101000 *
b101000 2
b101000 B

#1410000
0!
04

#1415000
1!
14
b10001010 F

#1416000
b101001 *
b101001 2
b101001 B

#1420000
0!
04

#1425000
1!
14
b10001011 F

#1426000
b101010 *
b101010 2
b101010 B

#1430000
0!
04

#1435000
1!
14
b10001100 F

#1436000
0)
b101011 2
0<
b10 J

#1440000
0!
04

#1445000
1!
0/
14
0A
b0 D
b10001101 F

#1450000
0!
04

#1455000
1!
1)
01
14
1<
b10001110 F

#1460000
0!
04

#1465000
1!
14
b10001111 F

#1470000
0!
04

#1475000
1!
0)
14
0<
b10010000 F
b11111010000 I

#1480000
0!
04

#1485000
1!
b11111010000 #
1$
14
b11111010000 6
17
b10010001 F
1G
0H

#1490000
0!
04

#1495000
1!
0$
14
07
b10010010 F
b101 J

#1500000
0!
04

#1505000
1!
14
b10010011 F

#1510000
0!
04

#1515000
1!
14
b10010100 F

#1520000
0!
04

#1525000
1!
14
b10010101 F

#1530000
0!
04

#1535000
1!
14
b10010110 F

#1540000
0!
04

#1545000
1!
14
b10010111 F
b1010 J

#1550000
0!
04

#1555000
1!
14
b10011000 F

#1560000
0!
04

#1565000
1!
14
b10011001 F

#1570000
0!
04

#1575000
1!
14
b10011010 F

#1580000
0!
04

#1585000
1!
14
b10011011 F

#1590000
0!
04

#1595000
1!
14
b10011100 F

#1600000
0!
04

#1605000
1!
14
b10011101 F

#1610000
0!
04

#1615000
1!
14
b10011110 F

#1620000
0!
04

#1625000
1!
14
b10011111 F

#1630000
0!
04

#1635000
1!
14
b10100000 F

